jsserialize.py
jsserialize-0.5.dist-info/METADATA
jsserialize-0.5.dist-info/WHEEL
jsserialize-0.5.dist-info/top_level.txt
jsserialize-0.5.dist-info/RECORD
