Metadata-Version: 2.1
Name: jsserialize
Version: 0.5
Summary: 1-step serialization to/from json: handles user classes and circular refs
Home-page: https://alcramer@bitbucket.org/alcramer/jsserialize.git
Author: Al Cramer
Author-email: ac2.71828@gmail.com
License: UNKNOWN
Keywords: json,serialize,serialization
Platform: UNKNOWN
Classifier: Programming Language :: Python :: 3
Classifier: License :: OSI Approved :: MIT License
Classifier: Operating System :: OS Independent
Requires-Python: >=3.6
